dbt/adapters/depp/__init__.py
dbt/adapters/depp/__version__.py
dbt/adapters/depp/adapter.py
dbt/adapters/depp/py.typed
dbt/adapters/depp/cli/__init__.py
dbt/adapters/depp/cli/main.py
dbt/adapters/depp/cli/commands/__init__.py
dbt/adapters/depp/cli/commands/experiment.py
dbt/adapters/depp/cli/commands/init.py
dbt/adapters/depp/cli/commands/inspect.py
dbt/adapters/depp/cli/commands/new_model.py
dbt/adapters/depp/cli/commands/validate.py
dbt/adapters/depp/cli/templates/example_model.py.jinja
dbt/adapters/depp/cli/templates/marimo_notebook.py.jinja
dbt/adapters/depp/cli/templates/profiles.yml.jinja
dbt/adapters/depp/cli/templates/python_model.py.jinja
dbt/adapters/depp/cli/utils/__init__.py
dbt/adapters/depp/cli/utils/data_exporter.py
dbt/adapters/depp/cli/utils/dependency_extractor.py
dbt/adapters/depp/cli/utils/marimo_generator.py
dbt/adapters/depp/config/__init__.py
dbt/adapters/depp/config/adapter_type.py
dbt/adapters/depp/config/connections.py
dbt/adapters/depp/config/credential_wrapper.py
dbt/adapters/depp/config/model_config.py
dbt/adapters/depp/config/profile_loader.py
dbt/adapters/depp/executors/__init__.py
dbt/adapters/depp/executors/abstract_executor.py
dbt/adapters/depp/executors/geo_pandas_executor.py
dbt/adapters/depp/executors/pandas_executor.py
dbt/adapters/depp/executors/polars_executor.py
dbt/adapters/depp/executors/result.py
dbt/adapters/depp/typing/__init__.py
dbt/adapters/depp/typing/base.py
dbt/adapters/depp/typing/dbt_objects.py
dbt/adapters/depp/utils/__init__.py
dbt/adapters/depp/utils/ast_utils.py
dbt/adapters/depp/utils/general.py
dbt/adapters/depp/utils/profile_parsing.py
dbt/adapters/depp/utils/profiling.py
dbt/adapters/depp/utils/validation.py
dbt/include/__init__.py
dbt/include/depp/__init__.py
dbt/include/depp/dbt_project.yml
dbt/include/depp/macros/materializations/table.sql
dbt_depp-0.2.1.dist-info/METADATA
dbt_depp-0.2.1.dist-info/WHEEL
dbt_depp-0.2.1.dist-info/entry_points.txt
dbt_depp-0.2.1.dist-info/licenses/LICENSE
dbt_depp-0.2.1.dist-info/RECORD
