Metadata-Version: 2.4
Name: dbt-depp
Version: 0.2.1
Summary: DBT Enexis Python Postgres adapter - Run python scripts from any dbt project.
Project-URL: Homepage, https://github.com/YassinCh/depp
Project-URL: Repository, https://github.com/YassinCh/depp
Author-email: Yassin Chibrani <y.chibrani@gmail.com>
License: MIT
License-File: LICENSE
Keywords: analytics,data-engineering,dbt,elt,etl,high-performance,pandas,polars,runtime
Classifier: Development Status :: 4 - Beta
Classifier: Intended Audience :: Developers
Classifier: License :: OSI Approved :: MIT License
Classifier: Programming Language :: Python :: 3
Classifier: Programming Language :: Python :: 3.12
Requires-Python: >=3.12
Requires-Dist: adbc-driver-postgresql>=1.8.0
Requires-Dist: asyncpg-stubs>=0.30.2
Requires-Dist: asyncpg<0.31.0,>=0.30.0
Requires-Dist: connectorx>=0.4.4
Requires-Dist: cyclopts>=3.24.0
Requires-Dist: dbt-core>=1.10.0
Requires-Dist: dbt-postgres>=1.9.1
Requires-Dist: geoalchemy2>=0.18.0
Requires-Dist: geopandas>=1.1.1
Requires-Dist: marimo>=0.17.7
Requires-Dist: momepy>=0.10.0
Requires-Dist: mypy>=1.18.2
Requires-Dist: numpy>=2.0.0
Requires-Dist: pandas-stubs>=2.3.2.250827
Requires-Dist: pandas>=1.5.3
Requires-Dist: polars>=1.33.1
Requires-Dist: pyarrow>=21.0.0
Requires-Dist: ruff>=0.14.4
Requires-Dist: snakeviz>=2.2.2
Requires-Dist: sqlalchemy>=2.0.43
Requires-Dist: types-geopandas>=1.1.1.20250829
Provides-Extra: dev
Requires-Dist: matplotlib>=3.5.2; extra == 'dev'
Requires-Dist: requests>=2.32.3; extra == 'dev'
